DefaultTypstCalculator.py
TypstCalculator.py
TypstCalculatorServer.py
TypstConverter.py
TypstParser.py
gen/TypstGrammarLexer.py
gen/TypstGrammarListener.py
gen/TypstGrammarParser.py
gen/__init__.py
typst_sympy_calculator-0.6.2.dist-info/LICENSE.txt
typst_sympy_calculator-0.6.2.dist-info/METADATA
typst_sympy_calculator-0.6.2.dist-info/WHEEL
typst_sympy_calculator-0.6.2.dist-info/top_level.txt
typst_sympy_calculator-0.6.2.dist-info/RECORD
